Points2D/ArrayPoints.py
Points2D/Directions.py
Points2D/Points.py
Points2D/__init__.py
points2d-0.13.0.dist-info/licenses/LICENSE
points2d-0.13.0.dist-info/METADATA
points2d-0.13.0.dist-info/WHEEL
points2d-0.13.0.dist-info/top_level.txt
points2d-0.13.0.dist-info/RECORD
