Metadata-Version: 2.4
Name: Points2D
Version: 0.13.0
Summary: A class for two-dimensional points
Author-email: luomeng007 <1502506285@qq.com>
License-Expression: GPL-3.0
Project-URL: Homepage, https://gitee.com/camarolm/Points2D
Project-URL: Bug Tracker, https://gitee.com/camarolm/Points2D/issues
Classifier: Development Status :: 3 - Alpha
Classifier: Programming Language :: Python :: 3.11
Classifier: Operating System :: OS Independent
Requires-Python: >=3.11
License-File: LICENSE
Dynamic: license-file
